{"owner_org": "9b5de831-ed9e-4949-9489-b06934456537", "maintainer": "http://standaarden.overheid.nl/owms/terms/Centraal_Bureau_voor_de_Statistiek", "relationships_as_object": [], "lod_stars": "4", "private": false, "maintainer_email": null, "num_tags": 0, "id": "8c9714e8-efbf-452e-96ca-60462533a700", "metadata_created": "2015-03-26T14:44:42.573851", "metadata_modified": "2015-04-06T03:25:55.384167", "author": null, "author_email": null, "isopen": true, "source": "cbs", "state": "active", "version": null, "maintainer_facet": "http://standaarden.overheid.nl/owms/terms/Centraal_Bureau_voor_de_Statistiek", "md_soortwijziging": ":updated", "license_id": "cc-by3", "contact_point": "cbs@test.com", "type": "dataset", "resources": [{"resource_group_id": "5ef88363-c5c4-4c67-8fe9-7e958b6c494c", "cache_last_updated": null, "bytesize": "115 rijen, 15 kolommen", "revision_timestamp": "2015-04-06T03:25:55.383276", "webstore_last_updated": null, "id": "80fd7572-8f1b-4fdf-84fa-3718d70d62aa", "size": null, "state": "active", "hash": "", "description": "", "format": "application/atom+xml", "tracking_summary": {"total": 0, "recent": 0}, "mimetype_inner": null, "url_type": null, "mimetype": null, "cache_url": null, "name": "Transport; bedrijfsgemiddelden, 1999", "created": "2015-04-06T05:25:55.417890", "url": "http://opendata.cbs.nl/ODataFeed/OData/37776", "webstore_url": null, "last_modified": "2001-11-19T13:33:00", "position": 0, "revision_id": "b2374913-2042-4188-809b-12cfc4e2e1aa", "resource_type": null}, {"resource_group_id": "5ef88363-c5c4-4c67-8fe9-7e958b6c494c", "cache_last_updated": null, "bytesize": "115 rijen, 15 kolommen", "revision_timestamp": "2015-04-06T03:25:55.383276", "webstore_last_updated": null, "id": "80b22235-8cd8-4888-afd3-c2e57850c2d6", "size": null, "state": "active", "hash": "", "description": "", "format": "JSON", "tracking_summary": {"total": 0, "recent": 0}, "mimetype_inner": null, "url_type": null, "mimetype": null, "cache_url": null, "name": "Transport; bedrijfsgemiddelden, 1999", "created": "2015-04-06T05:25:55.417920", "url": "http://opendata.cbs.nl/ODataApi/OData/37776", "webstore_url": null, "last_modified": "2001-11-19T13:33:00", "position": 1, "revision_id": "b2374913-2042-4188-809b-12cfc4e2e1aa", "resource_type": null}], "num_resources": 2, "tags": [], "title": "Transport; bedrijfsgemiddelden, 1999", "maintainer_displayname": "ZBO | Centraal Bureau voor de Statistiek", "tracking_summary": {"total": 0, "recent": 0}, "groups": [], "creator_user_id": "5dbeeaaa-578e-4850-95be-badc04de521d", "relationships_as_subject": [], "revision_timestamp": "2015-03-26T14:44:42.573851", "identifier": "37776", "name": "transport-bedrijfsgemiddelden-1999", "language": "nl-NL", "accrual_periodicity": "http://purl.org/cld/freq/irregular", "notes": "Gemiddelde uitkomsten per bedrijf m.b.t. opbrengsten - en \nkostenstructuur en bedrijfseconomische kengetallen.\n1999\nGewijzigd op 19 november 2001.\nVerschijningsfrequentie: Stopgezet.", "license_title": "CC-BY 3.0", "modified": "2001-11-19T13:33:00", "url": null, "license_url": "http://creativecommons.org/licenses/by/3.0/nl/legalcode", "organization": {"description": "", "title": "Centraal Bureau voor de Statistiek", "created": "2015-03-26T12:55:58.497408", "approval_status": "approved", "revision_timestamp": "2015-03-26T11:55:58.470550", "is_organization": true, "state": "active", "image_url": "20150326-115558.468124cbslogonl.gif", "revision_id": "9d6a567a-44b5-482a-a9dd-d6d81a243617", "type": "organization", "id": "9b5de831-ed9e-4949-9489-b06934456537", "name": "centraal-bureau-voor-de-statistiek"}, "revision_id": "16d8dad5-e0f5-4803-8977-f80960c33a4f", "landingpage": "http://opendata.cbs.nl/dataportaal/portal.html#tableId=37776"}