{
    "owner_org": "9b5de831-ed9e-4949-9489-b06934456537", 
    "maintainer": "http://standaarden.overheid.nl/owms/terms/Centraal_Bureau_voor_de_Statistiek", 
    "relationships_as_object": [], 
    "lod_stars": "4", 
    "private": false, 
    "maintainer_email": null, 
    "num_tags": 0, 
    "id": "bf21842b-d5d5-47ae-a494-95c3fc046da2", 
    "metadata_created": "2015-03-26T14:01:52.663815", 
    "metadata_modified": "2015-04-17T03:07:52.495133", 
    "author": null, 
    "author_email": null, 
    "isopen": true, 
    "source": "cbs", 
    "state": "active", 
    "version": null, 
    "maintainer_facet": "http://standaarden.overheid.nl/owms/terms/Centraal_Bureau_voor_de_Statistiek", 
    "md_soortwijziging": ":updated", 
    "license_id": "cc-by3", 
    "contact_point": "cbs@test.com", 
    "type": "dataset", 
    "resources": [
        {
            "resource_group_id": "c77d2558-afbe-4dd8-8752-a4379c5a721b", 
            "cache_last_updated": null, 
            "bytesize": "4 rijen, 96 kolommen", 
            "revision_timestamp": "2015-04-17T03:07:52.494290", 
            "webstore_last_updated": null, 
            "id": "1a95d058-89fe-4af3-ac8e-ddaeddc99efc", 
            "size": null, 
            "state": "active", 
            "hash": "", 
            "description": "", 
            "format": "application/atom+xml", 
            "tracking_summary": {
                "total": 0, 
                "recent": 0
            }, 
            "mimetype_inner": null, 
            "url_type": null, 
            "mimetype": null, 
            "cache_url": null, 
            "name": "ICT finan. sector bedrijfsgrootte, 2006", 
            "created": "2015-04-17T05:07:52.621621", 
            "url": "http://opendata.cbs.nl/ODataFeed/OData/71769ned", 
            "webstore_url": null, 
            "last_modified": "2010-01-28T06:00:00", 
            "position": 0, 
            "revision_id": "0307c859-eac5-4dc9-93de-f77613fb0e22", 
            "resource_type": null
        }, 
        {
            "resource_group_id": "c77d2558-afbe-4dd8-8752-a4379c5a721b", 
            "cache_last_updated": null, 
            "bytesize": "4 rijen, 96 kolommen", 
            "revision_timestamp": "2015-04-17T03:07:52.494290", 
            "webstore_last_updated": null, 
            "id": "f4c7dd11-dbf6-49e6-a1e5-ffb787a7e29b", 
            "size": null, 
            "state": "active", 
            "hash": "", 
            "description": "", 
            "format": "JSON", 
            "tracking_summary": {
                "total": 0, 
                "recent": 0
            }, 
            "mimetype_inner": null, 
            "url_type": null, 
            "mimetype": null, 
            "cache_url": null, 
            "name": "ICT finan. sector bedrijfsgrootte, 2006", 
            "created": "2015-04-17T05:07:52.621650", 
            "url": "http://opendata.cbs.nl/ODataApi/OData/71769ned", 
            "webstore_url": null, 
            "last_modified": "2010-01-28T06:00:00", 
            "position": 1, 
            "revision_id": "0307c859-eac5-4dc9-93de-f77613fb0e22", 
            "resource_type": null
        }
    ], 
    "num_resources": 2, 
    "tags": [], 
    "title": "ICT finan. sector bedrijfsgrootte, 2006", 
    "maintainer_displayname": "ZBO | Centraal Bureau voor de Statistiek", 
    "tracking_summary": {
        "total": 0, 
        "recent": 0
    }, 
    "groups": [], 
    "creator_user_id": "5dbeeaaa-578e-4850-95be-badc04de521d", 
    "relationships_as_subject": [], 
    "revision_timestamp": "2015-03-26T14:01:52.663815", 
    "identifier": "71769ned", 
    "name": "ict-finan-sector-bedrijfsgrootte-2006", 
    "language": "nl-NL", 
    "accrual_periodicity": "http://purl.org/cld/freq/irregular", 
    "notes": "\nDeze tabel bevat gegevens over het gebruik van informatie- en \ncommunicatietechnologie (ICT) door bedrijven. Het gaat daarbij om:\n- het gebruik van computers; \n- ICT-systemen voor de kantooradministratie;\n- interne en externe netwerken, waaronder internet;\n- software en toepassing ervan;\n- (problemen bij) het werven van ICT-specialisten;\n- uitbesteding van werk van ICT-specialisten; \n- communicatie met overheden via internet;\n- de mate waarin de bedrijven het internet gebruiken voor in- en verkoop.\n\nDe gegevens hebben betrekking op bedrijven met 10 en meer werkzame\npersonen in de financi\u00eble sector. Peildatum daarbij is 31 december. \nDe gegevens zijn uitgesplitst naar bedrijfsafdeling (gebaseerd op de \nStandaardbedrijfsindeling (SBI'93)):\nOverige geldscheppende instellingen (SBI'93, code 6512) en Overige \nkredietverlening (SBI'93, code 6522), Levensverzekeringen, \nnaturaverzekeringen en spaarkassen (SBI'93, code 6601),\nSchadeverzekeringen (SBI'93, code 6603), de bedrijfstak Activiteiten ten \nbehoeve van of verwant aan financi\u00eble instellingen (SBI'93, code 67), \nexclusief de Optie-en effectenbeurzen (SBI'93, code 6711), exclusief de \nverzekeringsbeurzen (SBI'93, code 67201) en exclusief de Waarborgfondsen \n(SBI'93, code 67204).\n\nGegevens beschikbaar over het jaar 2006.\n\nWijziging per 24 december 2009:\nVanwege een aanpassing in de methode zijn de oude gegevens in deze tabel \nvervangen door nieuwe gegevens.\nBehalve bij de gegevens over bedrijven met cryptografische protocollen en \nde in- en verkopen via externe netwerken is de omvang van de correcties \nminimaal.\n\nStatus van de cijfers:\nDe cijfers zijn definitief.\n\nWanneer komen er nieuwe cijfers? \nVoor elk nieuw verslagjaar wordt er een nieuwe tabel gemaakt. \nDe tabel over 2007 komt in december 2008 beschikbaar.\n\n", 
    "license_title": "CC-BY 3.0", 
    "modified": "2010-01-28T06:00:00", 
    "url": null, 
    "license_url": "http://creativecommons.org/licenses/by/3.0/nl/legalcode", 
    "organization": {
        "description": "", 
        "title": "Centraal Bureau voor de Statistiek", 
        "created": "2015-03-26T12:55:58.497408", 
        "approval_status": "approved", 
        "revision_timestamp": "2015-03-26T11:55:58.470550", 
        "is_organization": true, 
        "state": "active", 
        "image_url": "20150326-115558.468124cbslogonl.gif", 
        "revision_id": "9d6a567a-44b5-482a-a9dd-d6d81a243617", 
        "type": "organization", 
        "id": "9b5de831-ed9e-4949-9489-b06934456537", 
        "name": "centraal-bureau-voor-de-statistiek"
    }, 
    "revision_id": "a0fba794-a566-4a2e-8bec-91e1448f976e", 
    "landingpage": "http://opendata.cbs.nl/dataportaal/portal.html#tableId=71769ned"
}