{
    "license_title": "CC-0", 
    "maintainer": "http://standaarden.overheid.nl/owms/terms/Rijkswaterstaat", 
    "relationships_as_object": [], 
    "lod_stars": "0", 
    "private": false, 
    "maintainer_email": "servicedesk-data@rws.nl", 
    "num_tags": 1, 
    "modified": "2011-09-19", 
    "id": "a688e615-47a8-415c-820f-ae8dcf0210ba", 
    "metadata_created": "2015-03-26T13:07:48.763443", 
    "metadata_modified": "2015-04-11T01:47:13.700204", 
    "author": "http://standaarden.overheid.nl/owms/terms/Rijkswaterstaat", 
    "author_email": "servicedesk-data@rws.nl", 
    "state": "active", 
    "source": "ngr", 
    "theme": "http://standaarden.overheid.nl/owms/terms/Organisatie_en_beleid", 
    "version": null, 
    "md_soortwijziging": ":updated", 
    "spatial": "Nederland", 
    "license_id": "cc-0", 
    "contact_point": "ngr@test.com", 
    "type": "dataset", 
    "md_uri": "http://nationaalgeoregister.nl/geonetwork?uuid=ccff0271-261f-4010-9a1f-69eddb7334c0", 
    "resources": [
        {
            "resource_group_id": "929e1afb-fb8e-4939-873d-6369e98b4ae0", 
            "protocol": "OGC:WMS", 
            "cache_last_updated": null, 
            "revision_timestamp": "2015-04-11T01:47:13.699319", 
            "webstore_last_updated": null, 
            "id": "726c3ab7-987c-48c1-82b7-24f6c52d969e", 
            "size": null, 
            "state": "active", 
            "hash": "", 
            "description": "", 
            "format": "ogc:wms", 
            "tracking_summary": {
                "total": 0, 
                "recent": 0
            }, 
            "last_modified": null, 
            "url_type": null, 
            "mimetype": null, 
            "cache_url": null, 
            "name": "AAA1200", 
            "created": "2015-04-11T03:47:13.738817", 
            "url": "http://geoservices.rijkswaterstaat.nl/water_beheergrenzen", 
            "webstore_url": null, 
            "mimetype_inner": null, 
            "position": 0, 
            "revision_id": "5484a69c-7cd2-4b96-93a6-959ae578da0d", 
            "resource_type": null
        }, 
        {
            "resource_group_id": "929e1afb-fb8e-4939-873d-6369e98b4ae0", 
            "protocol": "OGC:WFS", 
            "cache_last_updated": null, 
            "revision_timestamp": "2015-04-11T01:47:13.699319", 
            "webstore_last_updated": null, 
            "id": "8b799f52-7685-435b-86a0-6200c3c94915", 
            "size": null, 
            "state": "active", 
            "hash": "", 
            "description": "", 
            "format": "ogc:wfs", 
            "tracking_summary": {
                "total": 0, 
                "recent": 0
            }, 
            "last_modified": null, 
            "url_type": null, 
            "mimetype": null, 
            "cache_url": null, 
            "name": "AAA1200", 
            "created": "2015-04-11T03:47:13.738841", 
            "url": "http://geoservices.rijkswaterstaat.nl/water_beheergrenzen", 
            "webstore_url": null, 
            "mimetype_inner": null, 
            "position": 1, 
            "revision_id": "5484a69c-7cd2-4b96-93a6-959ae578da0d", 
            "resource_type": null
        }
    ], 
    "num_resources": 2, 
    "tags": [
        {
            "vocabulary_id": null, 
            "display_name": "Regelgeving Grenzen bestuurlijk Vergunningen Water Bijlage II Eems Dollard verdraggebied Rijkswatere", 
            "name": "Regelgeving Grenzen bestuurlijk Vergunningen Water Bijlage II Eems Dollard verdraggebied Rijkswatere", 
            "revision_timestamp": "2015-03-26T13:07:48.763443", 
            "state": "active", 
            "id": "ec88d9e8-e444-4902-b664-ade952cb8028"
        }
    ], 
    "theme_facet": "http://standaarden.overheid.nl/owms/terms/Bestuur", 
    "maintainer_displayname": "Ministerie van Infrastructuur en Milieu | Rijkswaterstaat", 
    "theme_displayname": "Bestuur | Organisatie en beleid", 
    "landingpage": "", 
    "temporal_from": "2008-01-01", 
    "language": "nl-NL", 
    "tracking_summary": {
        "total": 0, 
        "recent": 0
    }, 
    "groups": [], 
    "creator_user_id": "53359fa1-154d-4d03-8408-3582c9e0dcbc", 
    "relationships_as_subject": [], 
    "revision_timestamp": "2015-03-26T13:07:48.763443", 
    "organization": {
        "description": "", 
        "created": "2015-03-26T12:56:19.147623", 
        "title": "Nationaal Georegister", 
        "name": "nationaal-georegister", 
        "revision_timestamp": "2015-03-26T11:56:19.121612", 
        "is_organization": true, 
        "state": "active", 
        "image_url": "20150326-115619.119226ngr.png", 
        "revision_id": "918c4dfd-7496-4ac4-8b0d-a95fe2682aa9", 
        "type": "organization", 
        "id": "a9a8e392-9f69-493e-8b44-4a1586725a66", 
        "approval_status": "approved"
    }, 
    "name": "eems-dollard-verdraggebied-vlakken", 
    "isopen": true, 
    "temporal_to": "2008-12-31", 
    "url": null, 
    "notes": "Eems Dollard verdraggebied vlakken wordt gebruikt voor de kaarten van de Waterregeling ingaande per 01-01-2012.", 
    "owner_org": "a9a8e392-9f69-493e-8b44-4a1586725a66", 
    "maintainer_facet": "http://standaarden.overheid.nl/owms/terms/Rijkswaterstaat", 
    "extras": [
        {
            "key": "subtheme_facet", 
            "value": "http://standaarden.overheid.nl/owms/terms/Organisatie_en_beleid"
        }
    ], 
    "license_url": "http://creativecommons.org/publicdomain/zero/1.0/deed.nl", 
    "title": "Eems Dollard verdraggebied (vlakken)", 
    "revision_id": "9dfd9239-eafb-402f-9a39-2120ae719dc8", 
    "identifier": "ccff0271-261f-4010-9a1f-69eddb7334c0"
}