{
    "owner_org": "9b5de831-ed9e-4949-9489-b06934456537", 
    "maintainer": "http://standaarden.overheid.nl/owms/terms/Centraal_Bureau_voor_de_Statistiek", 
    "relationships_as_object": [], 
    "lod_stars": "4", 
    "private": false, 
    "maintainer_email": null, 
    "num_tags": 0, 
    "id": "95758bdc-6efb-46d0-9c85-faa8a24b87ec", 
    "metadata_created": "2015-03-26T14:41:46.484997", 
    "metadata_modified": "2015-04-11T03:22:52.073780", 
    "author": null, 
    "author_email": null, 
    "isopen": true, 
    "source": "cbs", 
    "state": "active", 
    "version": null, 
    "maintainer_facet": "http://standaarden.overheid.nl/owms/terms/Centraal_Bureau_voor_de_Statistiek", 
    "md_soortwijziging": ":updated", 
    "license_id": "cc-by3", 
    "contact_point": "cbs@test.com", 
    "type": "dataset", 
    "resources": [
        {
            "resource_group_id": "db39e59a-4cf7-464f-8783-e7a0cdf3a5c4", 
            "cache_last_updated": null, 
            "bytesize": "101 rijen, 454 kolommen", 
            "revision_timestamp": "2015-04-11T03:22:52.072911", 
            "webstore_last_updated": null, 
            "id": "52149435-2df2-439e-ae4e-b403fe3c816e", 
            "size": null, 
            "state": "active", 
            "hash": "", 
            "description": "", 
            "format": "application/atom+xml", 
            "tracking_summary": {
                "total": 0, 
                "recent": 0
            }, 
            "mimetype_inner": null, 
            "url_type": null, 
            "mimetype": null, 
            "cache_url": null, 
            "name": "Historie landbouw en visserij, 1899-1999", 
            "created": "2015-04-11T05:22:52.118059", 
            "url": "http://opendata.cbs.nl/ODataFeed/OData/37858", 
            "webstore_url": null, 
            "last_modified": "2009-01-30T11:44:00", 
            "position": 0, 
            "revision_id": "8e2fe5ab-c4a8-4a7b-9521-c247a6136b79", 
            "resource_type": null
        }, 
        {
            "resource_group_id": "db39e59a-4cf7-464f-8783-e7a0cdf3a5c4", 
            "cache_last_updated": null, 
            "bytesize": "101 rijen, 454 kolommen", 
            "revision_timestamp": "2015-04-11T03:22:52.072911", 
            "webstore_last_updated": null, 
            "id": "2a77b04d-d737-4c5d-83c4-a7b294a9fb8a", 
            "size": null, 
            "state": "active", 
            "hash": "", 
            "description": "", 
            "format": "JSON", 
            "tracking_summary": {
                "total": 0, 
                "recent": 0
            }, 
            "mimetype_inner": null, 
            "url_type": null, 
            "mimetype": null, 
            "cache_url": null, 
            "name": "Historie landbouw en visserij, 1899-1999", 
            "created": "2015-04-11T05:22:52.118087", 
            "url": "http://opendata.cbs.nl/ODataApi/OData/37858", 
            "webstore_url": null, 
            "last_modified": "2009-01-30T11:44:00", 
            "position": 1, 
            "revision_id": "8e2fe5ab-c4a8-4a7b-9521-c247a6136b79", 
            "resource_type": null
        }
    ], 
    "num_resources": 2, 
    "tags": [], 
    "title": "Historie landbouw en visserij, 1899-1999", 
    "maintainer_displayname": "ZBO | Centraal Bureau voor de Statistiek", 
    "tracking_summary": {
        "total": 0, 
        "recent": 0
    }, 
    "groups": [], 
    "creator_user_id": "5dbeeaaa-578e-4850-95be-badc04de521d", 
    "relationships_as_subject": [], 
    "revision_timestamp": "2015-03-26T14:41:46.484997", 
    "identifier": "37858", 
    "name": "historie-landbouw-en-visserij-1899-1999", 
    "language": "nl-NL", 
    "accrual_periodicity": "http://purl.org/cld/freq/irregular", 
    "notes": "Landbouwbedrijven, arbeidskrachten, grondgebruik, akkerbouwgewassen,\nveilingaanvoer, veehouderij, mestproductie, kunstmestgebruik, prijzen\n1899- 1999.\nGewijzigd op 30 januari 2009.\nVerschijningsfrequentie: Stopgezet.", 
    "license_title": "CC-BY 3.0", 
    "modified": "2009-01-30T11:44:00", 
    "url": null, 
    "license_url": "http://creativecommons.org/licenses/by/3.0/nl/legalcode", 
    "organization": {
        "description": "", 
        "title": "Centraal Bureau voor de Statistiek", 
        "created": "2015-03-26T12:55:58.497408", 
        "approval_status": "approved", 
        "revision_timestamp": "2015-03-26T11:55:58.470550", 
        "is_organization": true, 
        "state": "active", 
        "image_url": "20150326-115558.468124cbslogonl.gif", 
        "revision_id": "9d6a567a-44b5-482a-a9dd-d6d81a243617", 
        "type": "organization", 
        "id": "9b5de831-ed9e-4949-9489-b06934456537", 
        "name": "centraal-bureau-voor-de-statistiek"
    }, 
    "revision_id": "9719ef57-d1bc-42a9-ad91-5e5e4de2766b", 
    "landingpage": "http://opendata.cbs.nl/dataportaal/portal.html#tableId=37858"
}